LICENSE
MANIFEST.in
README.md
requirements.txt
setup.cfg
setup.py
version
src/dnutils/__init__.py
src/dnutils/console.py
src/dnutils/dates.py
src/dnutils/debug.py
src/dnutils/logs.py
src/dnutils/math.py
src/dnutils/signals.py
src/dnutils/stats.py
src/dnutils/threads.py
src/dnutils/threadsafe.py
src/dnutils/tools.py
src/dnutils.egg-info/PKG-INFO
src/dnutils.egg-info/SOURCES.txt
src/dnutils.egg-info/dependency_links.txt
src/dnutils.egg-info/requires.txt
src/dnutils.egg-info/top_level.txt
src/dnutils/version/__init__.py
test/test_loggers.py
test/test_p3.py