Metadata-Version: 2.1
Name: dnutils
Version: 0.3.12
Summary: A collection of convenience tools for everyday Python programming
Home-page: https://spritinio.de/dnutils
Download-URL: https://github.com/danielnyga/dnutils/archive/0.3.12.tar.gz
Author: Daniel Nyga
Author-email: nyga@cs.uni-bremen.de
Keywords: testing,logging,threading,multithreading,debugging,tools,utilities
Classifier: Development Status :: 3 - Alpha
Classifier: Intended Audience :: Developers
Classifier: Topic :: Software Development :: Libraries :: Python Modules
Classifier: Topic :: System :: Logging
Classifier: Topic :: Utilities
Classifier: License :: OSI Approved :: MIT License
Classifier: Programming Language :: Python :: 3
Classifier: Programming Language :: Python :: 3.5
Classifier: Programming Language :: Python :: 3.6
Classifier: Programming Language :: Python :: 3.7
Classifier: Programming Language :: Python :: 3.8
License-File: LICENSE
